homealone/__init__.py
homealone/app.py
homealone/core.py
homealone/env.py
homealone/utils.py
homealone/interfaces/__init__.py
homealone/interfaces/ads1263Interface.py
homealone/interfaces/ads1x15Interface.py
homealone/interfaces/fileInterface.py
homealone/interfaces/gpioInterface.py
homealone/interfaces/i2cInterface.py
homealone/interfaces/mcp23017Interface.py
homealone/interfaces/osInterface.py
homealone/interfaces/owfsInterface.py
homealone/interfaces/serialInterface.py
homealone/interfaces/tc74Interface.py
homealone/interfaces/testInterface.py
homealone/interfaces/timeInterface.py
homealone/interfaces/tplinkInterface.py
homealone/interfaces/w1Interface.py
homealone/logging/__init__.py
homealone/logging/logging.py
homealone/remote/__init__.py
homealone/remote/proxyService.py
homealone/remote/remoteClient.py
homealone/remote/remoteService.py
homealone/remote/restInterface.py
homealone/resources/__init__.py
homealone/resources/electricalSensors.py
homealone/resources/extraResources.py
homealone/resources/tempControl.py
homealone/resources/thermostatControl.py
homealone/scheduler/__init__.py
homealone/scheduler/scheduler.py
homealone/scheduler/sunriseset.py
homealone-0.0.24.dist-info/LICENSE
homealone-0.0.24.dist-info/METADATA
homealone-0.0.24.dist-info/WHEEL
homealone-0.0.24.dist-info/top_level.txt
homealone-0.0.24.dist-info/RECORD
