Metadata-Version: 2.1
Name: homealone
Version: 0.0.24
Summary: Home automation platform
Author-email: Joe Buehl <jbuehl@buehltech.com>
Project-URL: Homepage, https://github.com/jbuehl/homealone
Project-URL: Bug Tracker, https://github.com/jbuehl/homealone/issues
Classifier: Programming Language :: Python :: 3
Classifier: License :: OSI Approved :: GNU General Public License (GPL)
Classifier: Operating System :: POSIX :: Linux
Classifier: Topic :: Home Automation
Requires-Python: >=3.5
License-File: LICENSE
